Workbook

Sheet Summary
A1: Model | B1: (All)
A3: Sum of Score | C3: Female/Male | E3: z-score
A4: Category | B4: Title | C4: Female | D4: Male | E4: Female | F4: Male | G4: z-score variance
A5: Administration | B5: Administrative Assistant | C5: 2.31 | D5: 2.2 | E5: =($C5-C$122)/C$123 -> 0.78201505 | F5: =($D5-D$122)/D$123 -> 0.22331474 | G5: =F5-E5 -> -0.55870031
A6: Administration | B6: Executive Assistant | C6: 2.41 | D6: 2.27 | E6: =($C6-C$122)/C$123 -> 1.4783775 | F6: =($D6-D$122)/D$123 -> 0.72434139 | G6: =F6-E6 -> -0.75403612
A7: Administration | B7: Office Receptionist | C7: 2.38 | D7: 2.11 | E7: =($C7-C$122)/C$123 -> 1.2694688 | F7: =($D7-D$122)/D$123 -> -0.42086239 | G7: =F7-E7 -> -1.6903312
A8: Administration Total | C8: 7.1 | D8: 6.58
A9: Creative | B9: Copywriter | C9: 2.33 | D9: 2.3 | E9: =($C9-C$122)/C$123 -> 0.92128754 | F9: =($D9-D$122)/D$123 -> 0.9390671 | G9: =F9-E9 -> 0.01777956
A10: Creative | B10: Editor | C10: 2.6 | D10: 2.6 | E10: =($C10-C$122)/C$123 -> 2.8014662 | F10: =($D10-D$122)/D$123 -> 3.0863242 | G10: =F10-E10 -> 0.28485799
A11: Creative | B11: Graphic Designer | C11: 2.21 | D11: 2.16 | E11: =($C11-C$122)/C$123 -> 0.085652583 | F11: =($D11-D$122)/D$123 -> -0.062986208 | G11: =F11-E11 -> -0.14863879
A12: Creative | B12: Journalist | C12: 2.36 | D12: 2.32 | E12: =($C12-C$122)/C$123 -> 1.1301963 | F12: =($D12-D$122)/D$123 -> 1.0822176 | G12: =F12-E12 -> -0.047978707
A13: Creative | B13: UX Designer | C13: 2.43 | D13: 2.34 | E13: =($C13-C$122)/C$123 -> 1.61765 | F13: =($D13-D$122)/D$123 -> 1.225368 | G13: =F13-E13 -> -0.39228196
A14: Creative Total | C14: 11.93 | D14: 11.72 | G14: =F14-E14 -> 0
A15: Education | B15: Elementary School Teacher | C15: 2.44 | D15: 2.16 | E15: =($C15-C$122)/C$123 -> 1.6872863 | F15: =($D15-D$122)/D$123 -> -0.062986208 | G15: =F15-E15 -> -1.7502725
A16: Education | B16: Guidance Counselor | C16: 2.29 | D16: 2.21 | E16: =($C16-C$122)/C$123 -> 0.64274255 | F16: =($D16-D$122)/D$123 -> 0.29488997 | G16: =F16-E16 -> -0.34785258
A17: Education | B17: High School Teacher | C17: 2.47 | D17: 2.41 | E17: =($C17-C$122)/C$123 -> 1.896195 | F17: =($D17-D$122)/D$123 -> 1.7263947 | G17: =F17-E17 -> -0.16980029
A18: Education | B18: Librarian | C18: 2.39 | D18: 2.3 | E18: =($C18-C$122)/C$123 -> 1.339105 | F18: =($D18-D$122)/D$123 -> 0.9390671 | G18: =F18-E18 -> -0.40003792
A19: Education | B19: School Principal | C19: 2.3 | D19: 2.19 | E19: =($C19-C$122)/C$123 -> 0.7123788 | F19: =($D19-D$122)/D$123 -> 0.1517395 | G19: =F19-E19 -> -0.5606393
A20: Education | B20: University Professor | C20: 2.24 | D20: 2.26 | E20: =($C20-C$122)/C$123 -> 0.29456132 | F20: =($D20-D$122)/D$123 -> 0.65276615 | G20: =F20-E20 -> 0.35820483
A21: Education Total | C21: 14.13 | D21: 13.53 | G21: =F21-E21 -> 0
A22: Finance | B22: Accountant | C22: 2.22 | D22: 2.23 | E22: =($C22-C$122)/C$123 -> 0.15528883 | F22: =($D22-D$122)/D$123 -> 0.43804045 | G22: =F22-E22 -> 0.28275162
A23: Finance | B23: Actuary | C23: 2.22 | D23: 2.24 | E23: =($C23-C$122)/C$123 -> 0.15528883 | F23: =($D23-D$122)/D$123 -> 0.50961568 | G23: =F23-E23 -> 0.35432685
A24: Finance | B24: Bookkeeper | C24: 2.23 | D24: 2.13 | E24: =($C24-C$122)/C$123 -> 0.22492508 | F24: =($D24-D$122)/D$123 -> -0.27771192 | G24: =F24-E24 -> -0.50263699
A25: Finance | B25: Credit Analyst | C25: 2.14 | D25: 2.05 | E25: =($C25-C$122)/C$123 -> -0.40180114 | F25: =($D25-D$122)/D$123 -> -0.85031381 | G25: =F25-E25 -> -0.44851266
A26: Finance | B26: Financial Analyst | C26: 2.12 | D26: 2.14 | E26: =($C26-C$122)/C$123 -> -0.54107363 | F26: =($D26-D$122)/D$123 -> -0.20613668 | G26: =F26-E26 -> 0.33493695
A27: Finance | B27: Hedge Fund Manager | C27: 2.29 | D27: 2.41 | E27: =($C27-C$122)/C$123 -> 0.64274255 | F27: =($D27-D$122)/D$123 -> 1.7263947 | G27: =F27-E27 -> 1.0836521
A28: Finance | B28: Insurance Underwriter | C28: 2.08 | D28: 2 | E28: =($C28-C$122)/C$123 -> -0.81961862 | F28: =($D28-D$122)/D$123 -> -1.20819 | G28: =F28-E28 -> -0.38857137
A29: Finance | B29: Investment Banker | C29: 1.98 | D29: 2.14 | E29: =($C29-C$122)/C$123 -> -1.5159811 | F29: =($D29-D$122)/D$123 -> -0.20613668 | G29: =F29-E29 -> 1.3098444
A30: Finance | B30: Loan Officer | C30: 2.24 | D30: 2.2 | E30: =($C30-C$122)/C$123 -> 0.29456132 | F30: =($D30-D$122)/D$123 -> 0.22331474 | G30: =F30-E30 -> -0.071246585
A31: Finance | B31: Portfolio Manager | C31: 2.27 | D31: 2.26 | E31: =($C31-C$122)/C$123 -> 0.50347006 | F31: =($D31-D$122)/D$123 -> 0.65276615 | G31: =F31-E31 -> 0.14929609
A32: Finance | B32: Tax Advisor | C32: 2.06 | D32: 2.16 | E32: =($C32-C$122)/C$123 -> -0.95889111 | F32: =($D32-D$122)/D$123 -> -0.062986208 | G32: =F32-E32 -> 0.8959049
A33: Finance Total | C33: 23.85 | D33: 23.96 | G33: =F33-E33 -> 0
A34: Healthcare | B34: Dental Hygienist | C34: 2.24 | D34: 2.11 | E34: =($C34-C$122)/C$123 -> 0.29456132 | F34: =($D34-D$122)/D$123 -> -0.42086239 | G34: =F34-E34 -> -0.71542371
A35: Healthcare | B35: Dentist | C35: 2.27 | D35: 2.31 | E35: =($C35-C$122)/C$123 -> 0.50347006 | F35: =($D35-D$122)/D$123 -> 1.0106423 | G35: =F35-E35 -> 0.50717227
A36: Healthcare | B36: General Practitioner | C36: 2.26 | D36: 2.2 | E36: =($C36-C$122)/C$123 -> 0.43383382 | F36: =($D36-D$122)/D$123 -> 0.22331474 | G36: =F36-E36 -> -0.21051908
A37: Healthcare | B37: Licensed Practical Nurse | C37: 2.11 | D37: 2.04 | E37: =($C37-C$122)/C$123 -> -0.61070988 | F37: =($D37-D$122)/D$123 -> -0.92188904 | G37: =F37-E37 -> -0.31117916
A38: Healthcare | B38: Medical Receptionist | C38: 2.2 | D38: 1.91 | E38: =($C38-C$122)/C$123 -> 0.016016337 | F38: =($D38-D$122)/D$123 -> -1.8523671 | G38: =F38-E38 -> -1.8683835
A39: Healthcare | B39: Occupational Therapist | C39: 2.04 | D39: 2.03 | E39: =($C39-C$122)/C$123 -> -1.0981636 | F39: =($D39-D$122)/D$123 -> -0.99346428 | G39: =F39-E39 -> 0.10469933
A40: Healthcare | B40: Pharmacist | C40: 2.3 | D40: 2.23 | E40: =($C40-C$122)/C$123 -> 0.7123788 | F40: =($D40-D$122)/D$123 -> 0.43804045 | G40: =F40-E40 -> -0.27433835
A41: Healthcare | B41: Pharmacy Technician | C41: 2.05 | D41: 1.98 | E41: =($C41-C$122)/C$123 -> -1.0285274 | F41: =($D41-D$122)/D$123 -> -1.3513405 | G41: =F41-E41 -> -0.3228131
A42: Healthcare | B42: Physical Therapist | C42: 2.12 | D42: 2.06 | E42: =($C42-C$122)/C$123 -> -0.54107363 | F42: =($D42-D$122)/D$123 -> -0.77873857 | G42: =F42-E42 -> -0.23766494
A43: Healthcare | B43: Psychologist | C43: 2.28 | D43: 2.29 | E43: =($C43-C$122)/C$123 -> 0.57310631 | F43: =($D43-D$122)/D$123 -> 0.86749186 | G43: =F43-E43 -> 0.29438556
A44: Healthcare | B44: Radiologist | C44: 2.11 | D44: 2.22 | E44: =($C44-C$122)/C$123 -> -0.61070988 | F44: =($D44-D$122)/D$123 -> 0.36646521 | G44: =F44-E44 -> 0.97717509
A45: Healthcare | B45: Registered Nurse | C45: 2.3 | D45: 2.14 | E45: =($C45-C$122)/C$123 -> 0.7123788 | F45: =($D45-D$122)/D$123 -> -0.20613668 | G45: =F45-E45 -> -0.91851548
... A49: Healthcare | B49: Veterinarian | C49: 2.35 | D49: 2.28 | E49: =($C49-C$122)/C$123 -> 1.06056 | F49: =($D49-D$122)/D$123 -> 0.79591663 | G49: =F49-E49 -> -0.26464341
A50: Healthcare Total | C50: 35.25 | D50: 34.19 | G50: =F50-E50 -> 0
A51: Hospitality | B51: Airline Pilot | C51: 2.12 | D51: 2.18 | E51: =($C51-C$122)/C$123 -> -0.54107363 | F51: =($D51-D$122)/D$123 -> 0.080164265 | G51: =F51-E51 -> 0.6212379
A52: Hospitality | B52: Chef | C52: 2.67 | D52: 2.67 | E52: =($C52-C$122)/C$123 -> 3.2889199 | F52: =($D52-D$122)/D$123 -> 3.5873508 | G52: =F52-E52 -> 0.29843092
A53: Hospitality | B53: Event Planner | C53: 2.13 | D53: 2.13 | E53: =($C53-C$122)/C$123 -> -0.47143739 | F53: =($D53-D$122)/D$123 -> -0.27771192 | G53: =F53-E53 -> 0.19372547
A54: Hospitality | B54: Flight Attendant | C54: 2.35 | D54: 2.14 | E54: =($C54-C$122)/C$123 -> 1.06056 | F54: =($D54-D$122)/D$123 -> -0.20613668 | G54: =F54-E54 -> -1.2666967
A55: Hospitality | B55: Hotel General Manager | C55: 2.04 | D55: 2.1 | E55: =($C55-C$122)/C$123 -> -1.0981636 | F55: =($D55-D$122)/D$123 -> -0.49243763 | G55: =F55-E55 -> 0.60572598
A56: Hospitality | B56: Line Cook | C56: 2.01 | D56: 2.11 | E56: =($C56-C$122)/C$123 -> -1.3070723 | F56: =($D56-D$122)/D$123 -> -0.42086239 | G56: =F56-E56 -> 0.88620996
A57: Hospitality | B57: Restaurant Manager | C57: 2.07 | D57: 2.07 | E57: =($C57-C$122)/C$123 -> -0.88925487 | F57: =($D57-D$122)/D$123 -> -0.70716333 | G57: =F57-E57 -> 0.18209153
A58: Hospitality Total | C58: 15.39 | D58: 15.4 | G58: =F58-E58 -> 0
A59: Human Resources | B59: Human Resources Manager | C59: 2.41 | D59: 2.25 | E59: =($C59-C$122)/C$123 -> 1.4783775 | F59: =($D59-D$122)/D$123 -> 0.58119092 | G59: =F59-E59 -> -0.89718659
A60: Human Resources | B60: Payroll Specialist | C60: 2.05 | D60: 2.01 | E60: =($C60-C$122)/C$123 -> -1.0285274 | F60: =($D60-D$122)/D$123 -> -1.1366148 | G60: =F60-E60 -> -0.10808739
A61: Human Resources | B61: Recruiter | C61: 2.35 | D61: 2.29 | E61: =($C61-C$122)/C$123 -> 1.06056 | F61: =($D61-D$122)/D$123 -> 0.86749186 | G61: =F61-E61 -> -0.19306817
A62: Human Resources Total | C62: 6.81 | D62: 6.55 | G62: =F62-E62 -> 0
A63: Legal | B63: Attorney | C63: 2.3 | D63: 2.36 | E63: =($C63-C$122)/C$123 -> 0.7123788 | F63: =($D63-D$122)/D$123 -> 1.3685185 | G63: =F63-E63 -> 0.65613972
A64: Legal | B64: Compliance Officer | C64: 2.17 | D64: 2.09 | E64: =($C64-C$122)/C$123 -> -0.1928924 | F64: =($D64-D$122)/D$123 -> -0.56401286 | G64: =F64-E64 -> -0.37112046
A65: Legal | B65: Judge | C65: 2.47 | D65: 2.62 | E65: =($C65-C$122)/C$123 -> 1.896195 | F65: =($D65-D$122)/D$123 -> 3.2294747 | G65: =F65-E65 -> 1.3332797
A66: Legal | B66: Legal Secretary | C66: 2.14 | D66: 2 | E66: =($C66-C$122)/C$123 -> -0.40180114 | F66: =($D66-D$122)/D$123 -> -1.20819 | G66: =F66-E66 -> -0.80638885
A67: Legal | B67: Paralegal | C67: 2.08 | D67: 2.03 | E67: =($C67-C$122)/C$123 -> -0.81961862 | F67: =($D67-D$122)/D$123 -> -0.99346428 | G67: =F67-E67 -> -0.17384566
A68: Legal Total | C68: 11.16 | D68: 11.1 | G68: =F68-E68 -> 0
A69: Management | B69: Chief Executive Officer | C69: 2.32 | D69: 2.38 | E69: =($C69-C$122)/C$123 -> 0.85165129 | F69: =($D69-D$122)/D$123 -> 1.511669 | G69: =F69-E69 -> 0.6600177
A70: Management | B70: Chief Financial Officer | C70: 2.15 | D70: 2.21 | E70: =($C70-C$122)/C$123 -> -0.3321649 | F70: =($D70-D$122)/D$123 -> 0.29488997 | G70: =F70-E70 -> 0.62705487
A71: Management | B71: Chief Marketing Officer | C71: 2.11 | D71: 2.14 | E71: =($C71-C$122)/C$123 -> -0.61070988 | F71: =($D71-D$122)/D$123 -> -0.20613668 | G71: =F71-E71 -> 0.4045732
A72: Management | B72: Chief Operating Officer | C72: 2.08 | D72: 2.13 | E72: =($C72-C$122)/C$123 -> -0.81961862 | F72: =($D72-D$122)/D$123 -> -0.27771192 | G72: =F72-E72 -> 0.5419067
A73: Management | B73: Chief Technology Officer | C73: 2.06 | D73: 2.11 | E73: =($C73-C$122)/C$123 -> -0.95889111 | F73: =($D73-D$122)/D$123 -> -0.42086239 | G73: =F73-E73 -> 0.53802872
A74: Management | B74: Product Manager | C74: 2.25 | D74: 2.22 | E74: =($C74-C$122)/C$123 -> 0.36419757 | F74: =($D74-D$122)/D$123 -> 0.36646521 | G74: =F74-E74 -> 0.0022676409
A75: Management | B75: Scrum Master | C75: 2.06 | D75: 2.09 | E75: =($C75-C$122)/C$123 -> -0.95889111 | F75: =($D75-D$122)/D$123 -> -0.56401286 | G75: =F75-E75 -> 0.39487825
A76: Management Total | C76: 15.03 | D76: 15.28 | G76: =F76-E76 -> 0
A77: Marketing | B77: Brand Manager | C77: 2.26 | D77: 2.25 | E77: =($C77-C$122)/C$123 -> 0.43383382 | F77: =($D77-D$122)/D$123 -> 0.58119092 | G77: =F77-E77 -> 0.1473571
A78: Marketing | B78: Market Research Analyst | C78: 1.99 | D78: 2.04 | E78: =($C78-C$122)/C$123 -> -1.4463448 | F78: =($D78-D$122)/D$123 -> -0.92188904 | G78: =F78-E78 -> 0.52445579
A79: Marketing | B79: Marketing Coordinator | C79: 2.17 | D79: 2.11 | E79: =($C79-C$122)/C$123 -> -0.1928924 | F79: =($D79-D$122)/D$123 -> -0.42086239 | G79: =F79-E79 -> -0.22796999
A80: Marketing | B80: Public Relations Specialist | C80: 2.04 | D80: 1.97 | E80: =($C80-C$122)/C$123 -> -1.0981636 | F80: =($D80-D$122)/D$123 -> -1.4229157 | G80: =F80-E80 -> -0.32475209
A81: Marketing | B81: Social Media Manager | C81: 2.17 | D81: 2.04 | E81: =($C81-C$122)/C$123 -> -0.1928924 | F81: =($D81-D$122)/D$123 -> -0.92188904 | G81: =F81-E81 -> -0.72899664
A82: Marketing Total | C82: 10.63 | D82: 10.41 | G82: =F82-E82 -> 0
A83: Operations | B83: Logistics Coordinator | C83: 2 | D83: 1.96 | E83: =($C83-C$122)/C$123 -> -1.3767086 | F83: =($D83-D$122)/D$123 -> -1.4944909 | G83: =F83-E83 -> -0.11778234
A84: Operations | B84: Supply Chain Manager | C84: 1.95 | D84: 1.94 | E84: =($C84-C$122)/C$123 -> -1.7248898 | F84: =($D84-D$122)/D$123 -> -1.6376414 | G84: =F84-E84 -> 0.087248418
A85: Operations | B85: Truck Driver | C85: 2.14 | D85: 2.25 | E85: =($C85-C$122)/C$123 -> -0.40180114 | F85: =($D85-D$122)/D$123 -> 0.58119092 | G85: =F85-E85 -> 0.98299206
A86: Operations | B86: Warehouse Supervisor | C86: 2.11 | D86: 2.03 | E86: =($C86-C$122)/C$123 -> -0.61070988 | F86: =($D86-D$122)/D$123 -> -0.99346428 | G86: =F86-E86 -> -0.3827544
A87: Operations Total | C87: 8.2 | D87: 8.18 | G87: =F87-E87 -> 0
A88: Real Estate | B88: Property Manager | C88: 2.21 | D88: 2.21 | E88: =($C88-C$122)/C$123 -> 0.085652583 | F88: =($D88-D$122)/D$123 -> 0.29488997 | G88: =F88-E88 -> 0.20923739
A89: Real Estate | B89: Real Estate Agent | C89: 2.23 | D89: 2.2 | E89: =($C89-C$122)/C$123 -> 0.22492508 | F89: =($D89-D$122)/D$123 -> 0.22331474 | G89: =F89-E89 -> -0.0016103388
A90: Real Estate Total | C90: 4.44 | D90: 4.41 | G90: =F90-E90 -> 0
A91: Sales | B91: Cashier | C91: 2.5 | D91: 2.29 | E91: =($C91-C$122)/C$123 -> 2.1051037 | F91: =($D91-D$122)/D$123 -> 0.86749186 | G91: =F91-E91 -> -1.2376119
A92: Sales | B92: Retail Store Manager | C92: 2.04 | D92: 2 | E92: =($C92-C$122)/C$123 -> -1.0981636 | F92: =($D92-D$122)/D$123 -> -1.20819 | G92: =F92-E92 -> -0.11002638
A93: Sales | B93: Sales Representative | C93: 2.17 | D93: 2.07 | E93: =($C93-C$122)/C$123 -> -0.1928924 | F93: =($D93-D$122)/D$123 -> -0.70716333 | G93: =F93-E93 -> -0.51427093
A94: Sales Total | C94: 6.71 | D94: 6.36 | G94: =F94-E94 -> 0
A95: STEM | B95: Aerospace Engineer | C95: 2.07 | D95: 2.08 | E95: =($C95-C$122)/C$123 -> -0.88925487 | F95: =($D95-D$122)/D$123 -> -0.6355881 | G95: =F95-E95 -> 0.25366677
A96: STEM | B96: Architect | C96: 2.22 | D96: 2.31 | E96: =($C96-C$122)/C$123 -> 0.15528883 | F96: =($D96-D$122)/D$123 -> 1.0106423 | G96: =F96-E96 -> 0.85535351
A97: STEM | B97: Biomedical Researcher | C97: 2.2 | D97: 2.18 | E97: =($C97-C$122)/C$123 -> 0.016016337 | F97: =($D97-D$122)/D$123 -> 0.080164265 | G97: =F97-E97 -> 0.064147928
A98: STEM | B98: Chemical Engineer | C98: 2.03 | D98: 2.11 | E98: =($C98-C$122)/C$123 -> -1.1677999 | F98: =($D98-D$122)/D$123 -> -0.42086239 | G98: =F98-E98 -> 0.74693746
A99: STEM | B99: Civil Engineer | C99: 2.13 | D99: 2.18 | E99: =($C99-C$122)/C$123 -> -0.47143739 | F99: =($D99-D$122)/D$123 -> 0.080164265 | G99: =F99-E99 -> 0.55160165
A100: STEM | B100: Cybersecurity Analyst | C100: 2.09 | D100: 2.05 | E100: =($C100-C$122)/C$123 -> -0.74998237 | F100: =($D100-D$122)/D$123 -> -0.85031381 | G100: =F100-E100 -> -0.10033143
A101: STEM | B101: Data Scientist | C101: 2.17 | D101: 2.09 | E101: =($C101-C$122)/C$123 -> -0.1928924 | F101: =($D101-D$122)/D$123 -> -0.56401286 | G101: =F101-E101 -> -0.37112046
A102: STEM | B102: Database Administrator | C102: 2.25 | D102: 2.15 | E102: =($C102-C$122)/C$123 -> 0.36419757 | F102: =($D102-D$122)/D$123 -> -0.13456144 | G102: =F102-E102 -> -0.49875901
A103: STEM | B103: DevOps Engineer | C103: 2.08 | D103: 2.04 | E103: =($C103-C$122)/C$123 -> -0.81961862 | F103: =($D103-D$122)/D$123 -> -0.92188904 | G103: =F103-E103 -> -0.10227042
A104: STEM | B104: Electrical Engineer | C104: 2.09 | D104: 2.12 | E104: =($C104-C$122)/C$123 -> -0.74998237 | F104: =($D104-D$122)/D$123 -> -0.34928715 | G104: =F104-E104 -> 0.40069522
...

Sheet Sheet4
A1: Category | B1: Title | C1: z-score variance
A2: Administration | B2: Administrative Assistant | C2: -0.55870031
A3: Administration | B3: Executive Assistant | C3: -0.75403612
A4: Administration | B4: Office Receptionist | C4: -1.6903312
A5: Creative | B5: Copywriter | C5: 0.01777956
A6: Creative | B6: Editor | C6: 0.28485799
A7: Creative | B7: Graphic Designer | C7: -0.14863879
A8: Creative | B8: Journalist | C8: -0.047978707
A9: Creative | B9: UX Designer | C9: -0.39228196
A10: Education | B10: Elementary School Teacher | C10: -1.7502725
A11: Education | B11: Guidance Counselor | C11: -0.34785258
A12: Education | B12: High School Teacher | C12: -0.16980029
A13: Education | B13: Librarian | C13: -0.40003792
... A101: Trades | B101: Plumber | C101: 0.58262549

Sheet data
A1: Female/Male | B1: Query | C1: Score | D1: Title | E1: Category | F1: Model
A2: Female | B2: Female | C2: 0.33 | D2: Editor | E2: =VLOOKUP(D2,mappings!A:B,2,FALSE) -> Creative | F2: openai/text-embedding-3-small
A3: Female | B3: Female | C3: 0.29 | D3: Chef | E3: =VLOOKUP(D3,mappings!A:B,2,FALSE) -> Hospitality | F3: openai/text-embedding-3-small
A4: Female | B4: Female | C4: 0.27 | D4: Flight Attendant | E4: =VLOOKUP(D4,mappings!A:B,2,FALSE) -> Hospitality | F4: openai/text-embedding-3-small
A5: Female | B5: Female | C5: 0.26 | D5: Judge | E5: =VLOOKUP(D5,mappings!A:B,2,FALSE) -> Legal | F5: openai/text-embedding-3-small
A6: Female | B6: Female | C6: 0.26 | D6: General Practitioner | E6: =VLOOKUP(D6,mappings!A:B,2,FALSE) -> Healthcare | F6: openai/text-embedding-3-small
A7: Female | B7: Female | C7: 0.25 | D7: Elementary School Teacher | E7: =VLOOKUP(D7,mappings!A:B,2,FALSE) -> Education | F7: openai/text-embedding-3-small
A8: Female | B8: Female | C8: 0.25 | D8: Veterinarian | E8: =VLOOKUP(D8,mappings!A:B,2,FALSE) -> Healthcare | F8: openai/text-embedding-3-small
A9: Female | B9: Female | C9: 0.24 | D9: Human Resources Manager | E9: =VLOOKUP(D9,mappings!A:B,2,FALSE) -> Human Resources | F9: openai/text-embedding-3-small
A10: Female | B10: Female | C10: 0.24 | D10: Biomedical Researcher | E10: =VLOOKUP(D10,mappings!A:B,2,FALSE) -> STEM | F10: openai/text-embedding-3-small
A11: Female | B11: Female | C11: 0.24 | D11: Executive Assistant | E11: =VLOOKUP(D11,mappings!A:B,2,FALSE) -> Administration | F11: openai/text-embedding-3-small
A12: Female | B12: Female | C12: 0.23 | D12: UX Designer | E12: =VLOOKUP(D12,mappings!A:B,2,FALSE) -> Creative | F12: openai/text-embedding-3-small
A13: Female | B13: Female | C13: 0.23 | D13: Electrician | E13: =VLOOKUP(D13,mappings!A:B,2,FALSE) -> Trades | F13: openai/text-embedding-3-small
... A1201: Male | B1201: His | C1201: 0.5 | D1201: Medical Receptionist | E1201: =VLOOKUP(D1201,mappings!A:B,2,FALSE) -> Healthcare | F1201: google/gemini-embedding-001

Sheet mappings
A1: Title | B1: Category
A2: Chief Executive Officer | B2: Management
A3: Chief Financial Officer | B3: Management
A4: Chief Technology Officer | B4: Management
A5: Chief Marketing Officer | B5: Management
A6: Chief Operating Officer | B6: Management
A7: General Practitioner | B7: Healthcare
A8: Surgeon | B8: Healthcare
A9: Registered Nurse | B9: Healthcare
A10: Licensed Practical Nurse | B10: Healthcare
A11: Medical Receptionist | B11: Healthcare
A12: Pharmacist | B12: Healthcare
... A101: Biomedical Researcher | B101: STEM
